{"GlobalPropertiesHash":"E8OQfVwIEEY1qQyHVfEtXzE8dUDc1o7GvW76k7xMwfM=","FingerprintPatternsHash":"gq3WsqcKBUGTSNle7RKKyXRIwh7M8ccEqOqYvIzoM04=","PropertyOverridesHash":"8ZRc1sGeVrPBx4lD717BgRaQekyh78QKV9SKsdt638U=","InputHashes":["vx166ehGCdKWZ\u002BwinQ9FBoZV/c2s1ZqU2XVbx4fWdX4=","8FfyiEyda\u002B26xhE/zj5I4iBP9Ajher\u002BN3q1n8WbOEuk=","jzD0teaIyEX7qbps\u002B9xsZJvkEjf5r3DEWg1TN9XP/KY=","4ur2teZ1tfpbUETunNfkBcQPhT3RBlfuMTJih/oohis=","zmvGK5q71Gw2TmNICxGfub7G4\u002BgKDGsEhgfkL3XyhH4=","YCy4Cz4K7US/fu8tcdo9hDKAbB1GIhQa1suDKU186Yo=","hM9P8Ff4LzYXAos\u002BoUEHi9GYfwkjYZkukIbXN98INGI=","rZWz9FNgJEd9sCJYZmXw0/qMKfPmDmMQj0JhXihpT2Y=","EhxYL/RNM2IF7ErIdTRj3NrXMSJHeSf9MRs2DrMv1mY="],"CachedAssets":{"YCy4Cz4K7US/fu8tcdo9hDKAbB1GIhQa1suDKU186Yo=":{"Identity":"C:\\Users\\Stepan\\Desktop\\Tic-Tac-Toe\\internship-entry-task\\Tic-Tac-Toe\\Tic-Tac-Toe\\wwwroot\\register.html","SourceId":"Tic-Tac-Toe","SourceType":"Discovered","ContentRoot":"C:\\Users\\Stepan\\Desktop\\Tic-Tac-Toe\\internship-entry-task\\Tic-Tac-Toe\\Tic-Tac-Toe\\wwwroot\\","BasePath":"_content/Tic-Tac-Toe","RelativePath":"register#[.{fingerprint}]?.html","AssetKind":"All","AssetMode":"All","AssetRole":"Primary","AssetMergeBehavior":null,"AssetMergeSource":"","RelatedAsset":null,"AssetTraitName":null,"AssetTraitValue":null,"Fingerprint":"xfhuojjkmy","Integrity":"zSeQfl6wBjEHs2Jhc4MWdygodWnhy0\u002BXNm2ZcV\u002BIqeQ=","CopyToOutputDirectory":"Never","CopyToPublishDirectory":"PreserveNewest","OriginalItemSpec":"wwwroot\\register.html","FileLength":614,"LastWriteTime":"2025-08-12T08:01:02.4193756+00:00"},"vx166ehGCdKWZ\u002BwinQ9FBoZV/c2s1ZqU2XVbx4fWdX4=":{"Identity":"C:\\Users\\Stepan\\Desktop\\Tic-Tac-Toe\\internship-entry-task\\Tic-Tac-Toe\\Tic-Tac-Toe\\wwwroot\\css\\style.css","SourceId":"Tic-Tac-Toe","SourceType":"Discovered","ContentRoot":"C:\\Users\\Stepan\\Desktop\\Tic-Tac-Toe\\internship-entry-task\\Tic-Tac-Toe\\Tic-Tac-Toe\\wwwroot\\","BasePath":"_content/Tic-Tac-Toe","RelativePath":"css/style#[.{fingerprint}]?.css","AssetKind":"All","AssetMode":"All","AssetRole":"Primary","AssetMergeBehavior":null,"AssetMergeSource":"","RelatedAsset":null,"AssetTraitName":null,"AssetTraitValue":null,"Fingerprint":"1j135m6cvd","Integrity":"fcdEDWk2/ABkfwcmhxxqhFwm\u002BhloXLeVj3\u002BT6bgQBAU=","CopyToOutputDirectory":"Never","CopyToPublishDirectory":"PreserveNewest","OriginalItemSpec":"wwwroot\\css\\style.css","FileLength":2141,"LastWriteTime":"2025-08-11T20:08:13.2679563+00:00"},"8FfyiEyda\u002B26xhE/zj5I4iBP9Ajher\u002BN3q1n8WbOEuk=":{"Identity":"C:\\Users\\Stepan\\Desktop\\Tic-Tac-Toe\\internship-entry-task\\Tic-Tac-Toe\\Tic-Tac-Toe\\wwwroot\\js\\auth.js","SourceId":"Tic-Tac-Toe","SourceType":"Discovered","ContentRoot":"C:\\Users\\Stepan\\Desktop\\Tic-Tac-Toe\\internship-entry-task\\Tic-Tac-Toe\\Tic-Tac-Toe\\wwwroot\\","BasePath":"_content/Tic-Tac-Toe","RelativePath":"js/auth#[.{fingerprint}]?.js","AssetKind":"All","AssetMode":"All","AssetRole":"Primary","AssetMergeBehavior":null,"AssetMergeSource":"","RelatedAsset":null,"AssetTraitName":null,"AssetTraitValue":null,"Fingerprint":"pz1q64c93b","Integrity":"ax3FXS1MaUCIMcx2I03TyUWEbMYnYNixcyOn0gTdRHE=","CopyToOutputDirectory":"Never","CopyToPublishDirectory":"PreserveNewest","OriginalItemSpec":"wwwroot\\js\\auth.js","FileLength":1172,"LastWriteTime":"2025-08-07T15:54:07.8936571+00:00"},"jzD0teaIyEX7qbps\u002B9xsZJvkEjf5r3DEWg1TN9XP/KY=":{"Identity":"C:\\Users\\Stepan\\Desktop\\Tic-Tac-Toe\\internship-entry-task\\Tic-Tac-Toe\\Tic-Tac-Toe\\wwwroot\\js\\game.js","SourceId":"Tic-Tac-Toe","SourceType":"Discovered","ContentRoot":"C:\\Users\\Stepan\\Desktop\\Tic-Tac-Toe\\internship-entry-task\\Tic-Tac-Toe\\Tic-Tac-Toe\\wwwroot\\","BasePath":"_content/Tic-Tac-Toe","RelativePath":"js/game#[.{fingerprint}]?.js","AssetKind":"All","AssetMode":"All","AssetRole":"Primary","AssetMergeBehavior":null,"AssetMergeSource":"","RelatedAsset":null,"AssetTraitName":null,"AssetTraitValue":null,"Fingerprint":"vovmr0ur50","Integrity":"7\u002BRNbGlvEjkn3LQwrknBKZLPHpLOWhnz2/bkFLVvHfU=","CopyToOutputDirectory":"Never","CopyToPublishDirectory":"PreserveNewest","OriginalItemSpec":"wwwroot\\js\\game.js","FileLength":1977,"LastWriteTime":"2025-08-12T10:19:24.8116259+00:00"},"zmvGK5q71Gw2TmNICxGfub7G4\u002BgKDGsEhgfkL3XyhH4=":{"Identity":"C:\\Users\\Stepan\\Desktop\\Tic-Tac-Toe\\internship-entry-task\\Tic-Tac-Toe\\Tic-Tac-Toe\\wwwroot\\login.html","SourceId":"Tic-Tac-Toe","SourceType":"Discovered","ContentRoot":"C:\\Users\\Stepan\\Desktop\\Tic-Tac-Toe\\internship-entry-task\\Tic-Tac-Toe\\Tic-Tac-Toe\\wwwroot\\","BasePath":"_content/Tic-Tac-Toe","RelativePath":"login#[.{fingerprint}]?.html","AssetKind":"All","AssetMode":"All","AssetRole":"Primary","AssetMergeBehavior":null,"AssetMergeSource":"","RelatedAsset":null,"AssetTraitName":null,"AssetTraitValue":null,"Fingerprint":"d3iz1d6w0o","Integrity":"WZvPwWQ5J5BMDyrIbzwXzj2U4I5zkCIidxbQLLpllqE=","CopyToOutputDirectory":"Never","CopyToPublishDirectory":"PreserveNewest","OriginalItemSpec":"wwwroot\\login.html","FileLength":595,"LastWriteTime":"2025-08-12T08:01:02.4374529+00:00"},"4ur2teZ1tfpbUETunNfkBcQPhT3RBlfuMTJih/oohis=":{"Identity":"C:\\Users\\Stepan\\Desktop\\Tic-Tac-Toe\\internship-entry-task\\Tic-Tac-Toe\\Tic-Tac-Toe\\wwwroot\\js\\lobby.js","SourceId":"Tic-Tac-Toe","SourceType":"Discovered","ContentRoot":"C:\\Users\\Stepan\\Desktop\\Tic-Tac-Toe\\internship-entry-task\\Tic-Tac-Toe\\Tic-Tac-Toe\\wwwroot\\","BasePath":"_content/Tic-Tac-Toe","RelativePath":"js/lobby#[.{fingerprint}]?.js","AssetKind":"All","AssetMode":"All","AssetRole":"Primary","AssetMergeBehavior":null,"AssetMergeSource":"","RelatedAsset":null,"AssetTraitName":null,"AssetTraitValue":null,"Fingerprint":"6c5ejhsm15","Integrity":"hinKyicQ\u002Bo12JsK8tk4XhWfGIbE65WH7PafgJNaIAU0=","CopyToOutputDirectory":"Never","CopyToPublishDirectory":"PreserveNewest","OriginalItemSpec":"wwwroot\\js\\lobby.js","FileLength":2352,"LastWriteTime":"2025-08-12T07:56:59.5466776+00:00"}},"CachedCopyCandidates":{}}